LSHCy/LSH.cpython-37m-darwin.so
LSHCy/__init__.py
LSHCy/sub/__init__.py
LSHCy/sub/helper.h
LSHCy/sub/helper.pxd
LSHCy/sub/wrong.cpython-37m-darwin.so
LSHCy-1.1.dist-info/LICENSE.txt
LSHCy-1.1.dist-info/METADATA
LSHCy-1.1.dist-info/WHEEL
LSHCy-1.1.dist-info/top_level.txt
LSHCy-1.1.dist-info/RECORD
